[
  {
    "id": "1",
    "name": "Lê Khải",
    "picture": "assets/images/users/leekhai.png",
    "email": "leekhai18@gmail.com",
    "phone": "0328372204"
  },
  {
    "id": "2",
    "name": "Lê Kim",
    "picture": "assets/images/users/leekim.png",
    "email": "leekim@gmail.com",
    "phone": "0328372204"
  },
  {
    "id": "3",
    "name": "Đăng Khôi",
    "picture": "assets/images/users/dangkhoi.png",
    "email": "anhthunguyen@gmail.com",
    "phone": "0328372204"
  },
  {
    "id": "4",
    "name": "Nguyễn Tuấn Anh",
    "picture": "assets/images/users/tuananh.png",
    "email": "nguyentuananh@gmail.com",
    "phone": "0328372204"
  },
  {
    "id": "5",
    "name": "Phạm Băng",
    "picture": "assets/images/users/phambang.png",
    "email": "bangpham@gmail.com",
    "phone": "0328372204"
  },
  {
    "id": "6",
    "name": "Khả Như",
    "picture": "assets/images/users/khanhu.png",
    "email": "bangpham@gmail.com",
    "phone": "0328372204"
  },
  {
    "id": "7",
    "name": "Phát Nguyễn",
    "picture": "assets/images/users/phatnguyen.jpg",
    "email": "phatnguyen@gmail.com",
    "phone": "0328372204"
  },
  {
    "id": "8",
    "name": "Kiều Anh",
    "picture": "assets/images/users/kieuanh.jpg",
    "email": "kieuanh@gmail.com",
    "phone": "0328372204"
  },
  {
    "id": "9",
    "name": "Quốc Đại",
    "picture": "assets/images/users/quocdai.jpg",
    "email": "quocdai@gmail.com",
    "phone": "0328372204"
  },
  {
    "id": "10",
    "name": "Cường Đô La",
    "picture": "assets/images/users/cuongdola.jpg",
    "email": "cuongdola@gmail.com",
    "phone": "0328372204"
  },
  {
    "id": "11",
    "name": "Lê Minh",
    "picture": "assets/images/users/leminh.png",
    "email": "leminh@gmail.com",
    "phone": "0328372204"
  },
  {
    "id": "12",
    "name": "Nguyên Lam",
    "picture": "assets/images/users/nguyenlam.jpg",
    "email": "nguyenlam@gmail.com",
    "phone": "0328372204"
  },
  {
    "id": "13",
    "name": "Đạt Nguyễn",
    "picture": "assets/images/users/datnguyen.jpg",
    "email": "datnguyen@gmail.com",
    "phone": "0328372204"
  },
  {
    "id": "14",
    "name": "Phương Tuyền",
    "picture": "assets/images/users/phuongtuyen.jpg",
    "email": "phuongtuyen@gmail.com",
    "phone": "0328372204"
  },
  {
    "id": "15",
    "name": "Phương Vy",
    "picture": "assets/images/users/phuongvy.jpg",
    "email": "phuongvy@gmail.com",
    "phone": "0328372204"
  },
  {
    "id": "16",
    "name": "Kim Cúc",
    "picture": "assets/images/users/kimcuc.jpg",
    "email": "kimcuc@gmail.com",
    "phone": "0328372204"
  },
  {
    "id": "17",
    "name": "Duy Anh",
    "picture": "assets/images/users/duyanh.jpg",
    "email": "duyanh@gmail.com",
    "phone": "0328372204"
  },
  {
    "id": "18",
    "name": "Công Phượng",
    "picture": "assets/images/users/congphuong.jpg",
    "email": "congphuong@gmail.com",
    "phone": "0328372204"
  },
  {
    "id": "19",
    "name": "Hoà Min",
    "picture": "assets/images/users/hoamy.jpg",
    "email": "hoamy@gmail.com",
    "phone": "0328372204"
  }
]